jaxfit/__init__.py
jaxfit/_optimize.py
jaxfit/common_jax.py
jaxfit/common_scipy.py
jaxfit/least_squares.py
jaxfit/loss_functions.py
jaxfit/minpack.py
jaxfit/trf.py
jaxfit-0.0.5.dist-info/LICENSE.txt
jaxfit-0.0.5.dist-info/METADATA
jaxfit-0.0.5.dist-info/WHEEL
jaxfit-0.0.5.dist-info/top_level.txt
jaxfit-0.0.5.dist-info/RECORD
